zope.app.debug-4.0.0-py2.7-nspkg.pth
zope/app/debug/__init__.py
zope/app/debug/debug.py
zope/app/debug/tests/__init__.py
zope/app/debug/tests/ftesting.zcml
zope/app/debug/tests/test_debug.py
zope.app.debug-4.0.0.dist-info/DESCRIPTION.rst
zope.app.debug-4.0.0.dist-info/METADATA
zope.app.debug-4.0.0.dist-info/RECORD
zope.app.debug-4.0.0.dist-info/WHEEL
zope.app.debug-4.0.0.dist-info/metadata.json
zope.app.debug-4.0.0.dist-info/namespace_packages.txt
zope.app.debug-4.0.0.dist-info/top_level.txt
