Metadata-Version: 2.0
Name: zope.app.debug
Version: 4.0.0
Summary: Zope Debug Mode
Home-page: http://github.com/zopefoundation/zope.app.debug
Author: Zope Corporation and Contributors
Author-email: zope-dev@zope.org
License: ZPL 2.1
Keywords: zope3 webdav
Platform: UNKNOWN
Classifier: Development Status :: 5 - Production/Stable
Classifier: Environment :: Web Environment
Classifier: Intended Audience :: Developers
Classifier: License :: OSI Approved :: Zope Public License
Classifier: Programming Language :: Python
Classifier: Natural Language :: English
Classifier: Operating System :: OS Independent
Classifier: Topic :: Internet :: WWW/HTTP
Classifier: Framework :: Zope3
Classifier: Programming Language :: Python
Classifier: Programming Language :: Python :: 2
Classifier: Programming Language :: Python :: 2.7
Classifier: Programming Language :: Python :: 3
Classifier: Programming Language :: Python :: 3.4
Classifier: Programming Language :: Python :: 3.5
Classifier: Programming Language :: Python :: 3.6
Classifier: Programming Language :: Python :: Implementation :: CPython
Classifier: Programming Language :: Python :: Implementation :: PyPy
Requires-Dist: setuptools
Requires-Dist: zope.app.appsetup
Requires-Dist: zope.app.publication
Requires-Dist: zope.publisher
Provides-Extra: test
Requires-Dist: zope.component; extra == 'test'
Requires-Dist: zope.principalregistry; extra == 'test'
Requires-Dist: zope.site; extra == 'test'
Requires-Dist: zope.testing; extra == 'test'
Requires-Dist: zope.testrunner; extra == 'test'
Requires-Dist: zope.traversing; extra == 'test'
